[
  {
    "key": "datr",
    "value": "ksgvaV4dG2ha_tJymbse6iTa",
    "expires": "2027-01-07T08:08:47.000Z",
    "maxAge": 34560000,
    "domain": "facebook.com",
    "path": "/",
    "secure": true,
    "httpOnly": true,
    "hostOnly": false,
    "creation": "2025-12-03T08:08:44.148Z",
    "lastAccessed": "2025-12-03T08:08:47.880Z",
    "sameSite": "none"
  },
  {
    "key": "sb",
    "value": "ksgvaW_QL7GFgwPRXM_xGq6f",
    "domain": "facebook.com",
    "path": "/",
    "hostOnly": false,
    "creation": "2025-12-03T08:08:44.150Z",
    "lastAccessed": "2025-12-03T08:08:47.880Z"
  },
  {
    "key": "c_user",
    "value": "61559381730491",
    "domain": "facebook.com",
    "path": "/",
    "hostOnly": false,
    "creation": "2025-12-03T08:08:44.150Z",
    "lastAccessed": "2025-12-03T08:08:47.880Z"
  },
  {
    "key": "xs",
    "value": "43%3Aqu1umhKK2BlqPg%3A2%3A1764739324%3A-1%3A-1",
    "domain": "facebook.com",
    "path": "/",
    "hostOnly": false,
    "creation": "2025-12-03T08:08:44.151Z",
    "lastAccessed": "2025-12-03T08:08:47.880Z"
  },
  {
    "key": "fr",
    "value": "0c68H3xY8ii2d9UUU.AWe7QZP7TGbzQsGYJNx8kumnmQwQgVmIKUXhwx77KQI4APK1TDY.BpL8iS..AAA.0.0.BpL_AM.AWcnzn2HDwnv4CyKuPUWGek9Ntg",
    "expires": "2026-03-03T08:08:44.000Z",
    "maxAge": 7776000,
    "domain": "facebook.com",
    "path": "/",
    "secure": true,
    "httpOnly": true,
    "hostOnly": false,
    "creation": "2025-12-03T08:08:44.151Z",
    "lastAccessed": "2025-12-03T08:08:47.880Z",
    "sameSite": "none"
  },
  {
    "key": "locale",
    "value": "en_US",
    "domain": "facebook.com",
    "path": "/",
    "hostOnly": false,
    "creation": "2025-12-03T08:08:44.151Z",
    "lastAccessed": "2025-12-03T08:08:47.880Z"
  },
  {
    "key": "ps_l",
    "value": "1",
    "domain": "facebook.com",
    "path": "/",
    "hostOnly": false,
    "creation": "2025-12-03T08:08:44.151Z",
    "lastAccessed": "2025-12-03T08:08:47.880Z"
  },
  {
    "key": "ps_n",
    "value": "1",
    "domain": "facebook.com",
    "path": "/",
    "hostOnly": false,
    "creation": "2025-12-03T08:08:44.151Z",
    "lastAccessed": "2025-12-03T08:08:47.880Z"
  }
]